odoo/addons/delivery_carrier_customer_info/README.rst
odoo/addons/delivery_carrier_customer_info/__init__.py
odoo/addons/delivery_carrier_customer_info/__manifest__.py
odoo/addons/delivery_carrier_customer_info/i18n/delivery_carrier_customer_info.pot
odoo/addons/delivery_carrier_customer_info/i18n/es.po
odoo/addons/delivery_carrier_customer_info/i18n/it.po
odoo/addons/delivery_carrier_customer_info/models/__init__.py
odoo/addons/delivery_carrier_customer_info/models/res_partner.py
odoo/addons/delivery_carrier_customer_info/models/res_partner_delivery_info.py
odoo/addons/delivery_carrier_customer_info/readme/CONTRIBUTORS.rst
odoo/addons/delivery_carrier_customer_info/readme/DESCRIPTION.rst
odoo/addons/delivery_carrier_customer_info/security/ir.model.access.csv
odoo/addons/delivery_carrier_customer_info/static/description/icon.png
odoo/addons/delivery_carrier_customer_info/static/description/index.html
odoo/addons/delivery_carrier_customer_info/views/menus.xml
odoo/addons/delivery_carrier_customer_info/views/res_partner.xml
odoo/addons/delivery_carrier_customer_info/views/res_partner_delivery_info.xml
odoo14_addon_delivery_carrier_customer_info-14.0.1.0.1.dev10.dist-info/METADATA
odoo14_addon_delivery_carrier_customer_info-14.0.1.0.1.dev10.dist-info/WHEEL
odoo14_addon_delivery_carrier_customer_info-14.0.1.0.1.dev10.dist-info/top_level.txt
odoo14_addon_delivery_carrier_customer_info-14.0.1.0.1.dev10.dist-info/RECORD
